bmtext/__init__.py
bmtext/meta.py
bmtext/pil.py
bmtext-0.0.2.dist-info/METADATA
bmtext-0.0.2.dist-info/WHEEL
bmtext-0.0.2.dist-info/top_level.txt
bmtext-0.0.2.dist-info/RECORD
