Metadata-Version: 2.1
Name: bmtext
Version: 0.0.2
Summary: Render text from BMFont bitmap fonts.
Home-page: UNKNOWN
Author: Mark Smith
Author-email: judy@judy.co.uk
License: UNKNOWN
Platform: UNKNOWN
Requires-Dist: attrs (~=19.3)
Provides-Extra: dev
Requires-Dist: black ; extra == 'dev'
Requires-Dist: pytest ; extra == 'dev'
Requires-Dist: twine ; extra == 'dev'
Requires-Dist: wheel ; extra == 'dev'
Requires-Dist: pillow (~=7.1) ; extra == 'dev'
Provides-Extra: pillow
Requires-Dist: pillow (~=7.1) ; extra == 'pillow'
